syn-0.0.14-py2.7-nspkg.pth
syn-0.0.14.dist-info/DESCRIPTION.rst
syn-0.0.14.dist-info/top_level.txt
syn-0.0.14.dist-info/WHEEL
syn-0.0.14.dist-info/metadata.json
syn-0.0.14.dist-info/namespace_packages.txt
syn-0.0.14.dist-info/RECORD
syn-0.0.14.dist-info/METADATA
syn/metadata.yml
syn/globals.py
syn/cython/__init__.py
syn/cython/c/__init__.py
syn/cython/b/__init__.py
syn/base_utils/tree.py
syn/base_utils/order.py
syn/base_utils/hash.py
syn/base_utils/debug.py
syn/base_utils/filters.py
syn/base_utils/dict.py
syn/base_utils/repl.py
syn/base_utils/list.py
syn/base_utils/logic.py
syn/base_utils/iter.py
syn/base_utils/alg.py
syn/base_utils/str.py
syn/base_utils/context.py
syn/base_utils/rand.py
syn/base_utils/py.py
syn/base_utils/__init__.py
syn/base_utils/float.py
syn/base_utils/tests/test_iter.py
syn/base_utils/tests/test_filters.py
syn/base_utils/tests/test_order.py
syn/base_utils/tests/test_rand.py
syn/base_utils/tests/test_py.py
syn/base_utils/tests/test_hash.py
syn/base_utils/tests/test_float.py
syn/base_utils/tests/harvest1.py
syn/base_utils/tests/test_alg.py
syn/base_utils/tests/test_context.py
syn/base_utils/tests/test_dict.py
syn/base_utils/tests/test_repl.py
syn/base_utils/tests/metadata1.yml
syn/base_utils/tests/test_tree.py
syn/base_utils/tests/test_str.py
syn/base_utils/tests/test_debug.py
syn/base_utils/tests/__init__.py
syn/base_utils/tests/test_logic.py
syn/base_utils/tests/delete1.py
syn/base_utils/tests/test_list.py
syn/base_utils/tests/foo/foo
syn/type/__init__.py
syn/type/c/__init__.py
syn/type/tests/test_type.py
syn/type/tests/__init__.py
syn/type/b/__init__.py
syn/type/a/registry.py
syn/type/a/type.py
syn/type/a/ext.py
syn/type/a/__init__.py
syn/type/a/tests/test_type.py
syn/type/a/tests/test_ext.py
syn/type/a/tests/__init__.py
syn/type/a/tests/test_registry.py
syn/base/__init__.py
syn/base/c/__init__.py
syn/base/tests/test_base.py
syn/base/tests/__init__.py
syn/base/b/base.py
syn/base/b/wrapper.py
syn/base/b/utils.py
syn/base/b/examine.py
syn/base/b/__init__.py
syn/base/b/meta.py
syn/base/b/tests/test_meta.py
syn/base/b/tests/test_wrapper.py
syn/base/b/tests/test_utils.py
syn/base/b/tests/test_base.py
